jira.py
setup.py
jiraprinter.egg-info/PKG-INFO
jiraprinter.egg-info/SOURCES.txt
jiraprinter.egg-info/dependency_links.txt
jiraprinter.egg-info/entry_points.txt
jiraprinter.egg-info/requires.txt
jiraprinter.egg-info/top_level.txt