Metadata-Version: 1.1
Name: jiraprinter
Version: 0.0.0
Summary: Simple printing interface for jira
Home-page: UNKNOWN
Author: Ingo Fruend
Author-email: ingo.fruend@twentybn.com
License: MIT
Keywords: jira printing
Platform: UNKNOWN
Classifier: Development Status :: 3 - Alpha
Classifier: Intended Audience :: End Users/Desktop
Classifier: License :: OSI Approved :: MIT License
Classifier: Programming Language :: Python :: 3
Classifier: Programming Language :: Python :: 3 :: Only
